syssqlite2pkgsV4/__init__.py
syssqlite2pkgsV4-1.1.0.dist-info/METADATA
syssqlite2pkgsV4-1.1.0.dist-info/WHEEL
syssqlite2pkgsV4-1.1.0.dist-info/top_level.txt
syssqlite2pkgsV4-1.1.0.dist-info/RECORD
