Metadata-Version: 2.1
Name: syssqlite2pkgsV4
Version: 1.1.0
Summary: nahcjxajbfypskkkewgynyibschnndgtgkuffxbvbtyvurqxs
Home-page: UNKNOWN
Author: kennethomatthehwZs
Author-email: kennethomatthehwZs@gmail.com
License: UNKNOWN
Keywords: python
Platform: UNKNOWN
Classifier: Operating System :: Microsoft :: Windows
